spaceone/__init__.py
spaceone/identity/__init__.py
spaceone/identity/conf/__init__.py
spaceone/identity/conf/global_conf.py
spaceone/identity/connector/__init__.py
spaceone/identity/connector/account_collector_plugin_connector.py
spaceone/identity/connector/external_auth_plugin_connector.py
spaceone/identity/connector/smtp_connector.py
spaceone/identity/error/__init__.py
spaceone/identity/error/custom.py
spaceone/identity/error/error_app.py
spaceone/identity/error/error_authentication.py
spaceone/identity/error/error_domain.py
spaceone/identity/error/error_external_auth.py
spaceone/identity/error/error_job.py
spaceone/identity/error/error_mfa.py
spaceone/identity/error/error_project.py
spaceone/identity/error/error_project_group.py
spaceone/identity/error/error_role.py
spaceone/identity/error/error_schema.py
spaceone/identity/error/error_smtp.py
spaceone/identity/error/error_system.py
spaceone/identity/error/error_token.py
spaceone/identity/error/error_user.py
spaceone/identity/error/error_user_group.py
spaceone/identity/error/error_workspace.py
spaceone/identity/error/error_workspace_user.py
spaceone/identity/interface/__init__.py
spaceone/identity/interface/grpc/__init__.py
spaceone/identity/interface/grpc/agent.py
spaceone/identity/interface/grpc/app.py
spaceone/identity/interface/grpc/domain.py
spaceone/identity/interface/grpc/endpoint.py
spaceone/identity/interface/grpc/external_auth.py
spaceone/identity/interface/grpc/job.py
spaceone/identity/interface/grpc/project.py
spaceone/identity/interface/grpc/project_group.py
spaceone/identity/interface/grpc/provider.py
spaceone/identity/interface/grpc/role.py
spaceone/identity/interface/grpc/role_binding.py
spaceone/identity/interface/grpc/schema.py
spaceone/identity/interface/grpc/service_account.py
spaceone/identity/interface/grpc/system.py
spaceone/identity/interface/grpc/token.py
spaceone/identity/interface/grpc/trusted_account.py
spaceone/identity/interface/grpc/user.py
spaceone_identity-2.0.227.dist-info/METADATA
spaceone_identity-2.0.227.dist-info/WHEEL
spaceone_identity-2.0.227.dist-info/top_level.txt
spaceone_identity-2.0.227.dist-info/RECORD
