Metadata-Version: 2.1
Name: spaceone-identity
Version: 2.0.227
Summary: SpaceONE identity service
Home-page: https://www.spaceone.dev/
Author: MEGAZONE SpaceONE Team
Author-email: admin@spaceone.dev
License: Apache License 2.0
Platform: UNKNOWN
Requires-Dist: spaceone-core
Requires-Dist: spaceone-api
Requires-Dist: langcodes
Requires-Dist: bcrypt
Requires-Dist: jinja2
Requires-Dist: fakeredis
Requires-Dist: pytz
